[
  {
    "name": "2000",
    "bridge_race": 282162411
  },
  {
    "name": "2001",
    "bridge_race": 284968955
  },
  {
    "name": "2002",
    "bridge_race": 287625193
  },
  {
    "name": "2003",
    "bridge_race": 290107933
  },
  {
    "name": "2004",
    "bridge_race": 292805298
  },
  {
    "name": "2005",
    "bridge_race": 295516599
  },
  {
    "name": "2006",
    "bridge_race": 298379912
  },
  {
    "name": "2007",
    "bridge_race": 301231207
  },
  {
    "name": "2008",
    "bridge_race": 304093966
  },
  {
    "name": "2009",
    "bridge_race": 306771529
  },
  {
    "name": "2010",
    "bridge_race": 308758105
  },
  {
    "name": "2011",
    "bridge_race": 311718857
  },
  {
    "name": "2012",
    "bridge_race": 314102623
  },
  {
    "name": "2013",
    "bridge_race": 316427395
  },
  {
    "name": "2014",
    "bridge_race": 318907401
  },
  {
    "name": "2015",
    "bridge_race": 321418820
  }
]